MANIFEST.in
README.rst
setup.py
threatbook_api/__init__.py
threatbook_api/domain_analysis_query.py
threatbook_api/email_analysis_query.py
threatbook_api/file_analysis_query.py
threatbook_api/ioc_query.py
threatbook_api/ip_analysis_query.py
threatbook_api/ip_reputation_query.py
threatbook_api.egg-info/PKG-INFO
threatbook_api.egg-info/SOURCES.txt
threatbook_api.egg-info/dependency_links.txt
threatbook_api.egg-info/requires.txt
threatbook_api.egg-info/top_level.txt
threatbook_api/example/__init__.py
threatbook_api/example/get_all_fields.py
threatbook_api/example/get_one_field.py
threatbook_api/example/get_some_fields.py