Metadata-Version: 1.0
Name: threatbook-api
Version: 0.1.6
Summary: UNKNOWN
Home-page: https://github.com/li010101/threatbook_api.git
Author: li010101
Author-email: liyaohui54@gmail.com
License: MIT Licence
Platform: UNKNOWN
